libgunshotmatch/comparison/__init__.py
libgunshotmatch/comparison/_utils.py
libgunshotmatch/comparison/projects.py
libgunshotmatch/comparison/unknowns.py
libgunshotmatch/consolidate/__init__.py
libgunshotmatch/consolidate/_fields.py
libgunshotmatch/consolidate/_spectra.py
libgunshotmatch/method/__init__.py
libgunshotmatch/method/_fields.py
libgunshotmatch/__init__.py
libgunshotmatch/datafile.py
libgunshotmatch/gzip_util.py
libgunshotmatch/peak.py
libgunshotmatch/project.py
libgunshotmatch/py.typed
libgunshotmatch/search.py
libgunshotmatch/utils.py
libgunshotmatch-1.0.0.dist-info/LICENSE
libgunshotmatch-1.0.0.dist-info/METADATA
libgunshotmatch-1.0.0.dist-info/WHEEL
libgunshotmatch-1.0.0.dist-info/entry_points.txt
libgunshotmatch-1.0.0.dist-info/RECORD
