Metadata-Version: 2.2
Name: libgunshotmatch
Version: 1.0.0
Summary: Base library for GunShotMatch.
Author-email: Dominic Davis-Foster <dominic@davis-foster.co.uk>
License: MIT
Home-page: https://github.com/GunShotMatch/libgunshotmatch
Project-URL: Issue Tracker, https://github.com/GunShotMatch/libgunshotmatch/issues
Project-URL: Source Code, https://github.com/GunShotMatch/libgunshotmatch
Project-URL: Documentation, https://libgunshotmatch.readthedocs.io/en/latest
Platform: Windows
Platform: macOS
Platform: Linux
Classifier: Development Status :: 3 - Alpha
Classifier: Intended Audience :: Developers
Classifier: License :: OSI Approved :: MIT License
Classifier: Operating System :: OS Independent
Classifier: Programming Language :: Python
Classifier: Programming Language :: Python :: 3 :: Only
Classifier: Programming Language :: Python :: 3.8
Classifier: Programming Language :: Python :: 3.9
Classifier: Programming Language :: Python :: 3.10
Classifier: Programming Language :: Python :: 3.11
Classifier: Programming Language :: Python :: 3.12
Classifier: Programming Language :: Python :: Implementation :: CPython
Classifier: Topic :: Software Development :: Libraries :: Python Modules
Classifier: Typing :: Typed
Requires-Python: >=3.8
Requires-Dist: attrs>=23.1.0
Requires-Dist: chemistry-tools>=v1.0.0b2
Requires-Dist: dom-toml[config]>=2.2.0
Requires-Dist: domdf-python-tools>=3.6.1
Requires-Dist: enum-tools>=0.10.0
Requires-Dist: mathematical>=0.5.1
Requires-Dist: numpy>=1.22
Requires-Dist: pandas>=2.0.3
Requires-Dist: pymassspec>=2.3.0
Requires-Dist: pyms-nist-search>=0.6.1
Requires-Dist: scipy>=1.9.0
Requires-Dist: sdjson>=0.4.0
Requires-Dist: tomli>=1.2.3; python_version < "3.11"
Requires-Dist: tomli-w>=1.0.0
Requires-Dist: typing-extensions>=4.12.2
